librapidsmpf/GIT_COMMIT
librapidsmpf/VERSION
librapidsmpf/__init__.py
librapidsmpf/_version.py
librapidsmpf/load.py
librapidsmpf/include/coro/attribute.hpp
librapidsmpf/include/coro/condition_variable.hpp
librapidsmpf/include/coro/coro.hpp
librapidsmpf/include/coro/default_executor.hpp
librapidsmpf/include/coro/event.hpp
librapidsmpf/include/coro/expected.hpp
librapidsmpf/include/coro/export.hpp
librapidsmpf/include/coro/fd.hpp
librapidsmpf/include/coro/generator.hpp
librapidsmpf/include/coro/io_notifier.hpp
librapidsmpf/include/coro/io_scheduler.hpp
librapidsmpf/include/coro/latch.hpp
librapidsmpf/include/coro/mutex.hpp
librapidsmpf/include/coro/poll.hpp
librapidsmpf/include/coro/queue.hpp
librapidsmpf/include/coro/ring_buffer.hpp
librapidsmpf/include/coro/semaphore.hpp
librapidsmpf/include/coro/shared_mutex.hpp
librapidsmpf/include/coro/sync_wait.hpp
librapidsmpf/include/coro/task.hpp
librapidsmpf/include/coro/task_container.hpp
librapidsmpf/include/coro/thread_pool.hpp
librapidsmpf/include/coro/time.hpp
librapidsmpf/include/coro/when_all.hpp
librapidsmpf/include/coro/when_any.hpp
librapidsmpf/include/coro/concepts/awaitable.hpp
librapidsmpf/include/coro/concepts/buffer.hpp
librapidsmpf/include/coro/concepts/executor.hpp
librapidsmpf/include/coro/concepts/promise.hpp
librapidsmpf/include/coro/concepts/range_of.hpp
librapidsmpf/include/coro/detail/awaiter_list.hpp
librapidsmpf/include/coro/detail/io_notifier_epoll.hpp
librapidsmpf/include/coro/detail/io_notifier_kqueue.hpp
librapidsmpf/include/coro/detail/poll_info.hpp
librapidsmpf/include/coro/detail/task_self_deleting.hpp
librapidsmpf/include/coro/detail/timer_handle.hpp
librapidsmpf/include/coro/detail/tl_expected.hpp
librapidsmpf/include/coro/detail/void_value.hpp
librapidsmpf/include/coro/net/connect.hpp
librapidsmpf/include/coro/net/hostname.hpp
librapidsmpf/include/coro/net/ip_address.hpp
librapidsmpf/include/coro/net/recv_status.hpp
librapidsmpf_cu13-25.10.0.dist-info/METADATA
librapidsmpf_cu13-25.10.0.dist-info/WHEEL
librapidsmpf_cu13-25.10.0.dist-info/entry_points.txt
librapidsmpf_cu13-25.10.0.dist-info/RECORD
