Metadata-Version: 2.1
Name: librapidsmpf-cu13
Version: 25.10.0
Summary: Multi-GPU and distributed-memory algorithms
Author: NVIDIA Corporation
License: Apache 2.0
Classifier: Intended Audience :: Developers
Classifier: Topic :: Database
Classifier: Topic :: Scientific/Engineering
Classifier: License :: OSI Approved :: Apache Software License
Classifier: Programming Language :: C++
Project-URL: Homepage, https://github.com/rapidsai/rapidsmpf
Requires-Python: >=3.10
Requires-Dist: libcudf-cu13==25.10.*,>=0.0.0a0
Requires-Dist: librmm-cu13==25.10.*,>=0.0.0a0
Requires-Dist: libucxx-cu13==0.46.*,>=0.0.0a0
Provides-Extra: test
